<?xml version="1.0" encoding="utf-8"?>
<resources>
    <string name="air_quality0">\'HKE \'+#aqi</string>
    <string name="air_quality1">\'HKE \'+#aqi</string>
    <string name="air_quality2">\'HKE \'+#aqi</string>
    <string name="air_quality3">\'HKE \'+#aqi</string>
    <string name="air_quality4">\'HKE \'+#aqi</string>
    <string name="air_quality5">\'HKE \'+#aqi</string>
    <string name="weather_null">Hava durumu bilgilerini almak için dokunun</string>
    <string name="weather_location_null">Konum bilgisi yok</string>
    <string name="weather_type_0">Açık</string>
    <string name="weather_type_1">Bulutlu</string>
    <string name="weather_type_2">Kapalı</string>
    <string name="weather_type_3">Sisli</string>
    <string name="weather_type_4">Şiddetli yağmur fırtınası</string>
    <string name="weather_type_5">Sağanak</string>
    <string name="weather_type_6">Yağmur fırtınası</string>
    <string name="weather_type_7">Gök gürültülü sağanak</string>
    <string name="weather_type_8">Yağmurlu</string>
    <string name="weather_type_9">Yoğun sağanak</string>
    <string name="weather_type_10">Yağmurlu</string>
    <string name="weather_type_11">Hafif yağmur</string>
    <string name="weather_type_12">Karla karışık yağmur</string>
    <string name="weather_type_13">Kar fırtınası</string>
    <string name="weather_type_14">Karlı</string>
    <string name="weather_type_15">Yoğun karlı</string>
    <string name="weather_type_16">Karlı</string>
    <string name="weather_type_17">Hafif karlı</string>
    <string name="weather_type_18">Şiddetli kum fırtınası</string>
    <string name="weather_type_19">Kum fırtınası</string>
    <string name="weather_type_20">Kum</string>
    <string name="weather_type_21">Toz fırtınası</string>
    <string name="weather_type_22">Dolu</string>
    <string name="weather_type_23">Toz</string>
    <string name="weather_type_24">Sisli</string>
    <string name="weather_type_25">Donan yağmur</string>
</resources>
